pytest_mutagen/__init__.py
pytest_mutagen/__main__.py
pytest_mutagen/_version.py
pytest_mutagen/mutagen.py
pytest_mutagen/mutation_session.py
pytest_mutagen/plugin.py
pytest_mutagen-1.3.dist-info/LICENSE
pytest_mutagen-1.3.dist-info/METADATA
pytest_mutagen-1.3.dist-info/WHEEL
pytest_mutagen-1.3.dist-info/entry_points.txt
pytest_mutagen-1.3.dist-info/top_level.txt
pytest_mutagen-1.3.dist-info/RECORD
