Metadata-Version: 2.1
Name: pytest-mutagen
Version: 1.3
Summary: Add the mutation testing feature to pytest
Home-page: https://github.com/hgoldstein95/pytest-mutagen
Author: Timothee Paquatte <timothee.paquatte@polytechnique.edu>, Harrison Goldstein <hgo@seas.upenn.edu>
Author-email: timothee.paquatte@polytechnique.edu
License: MIT
Keywords: python testing mutation mutant mutagen test
Platform: UNKNOWN
Classifier: Programming Language :: Python :: 3
Classifier: Programming Language :: Python :: 3 :: Only
Classifier: Programming Language :: Python :: 3.6
Classifier: Programming Language :: Python :: 3.7
Classifier: Programming Language :: Python :: 3.8
Classifier: License :: OSI Approved :: MIT License
Classifier: Operating System :: OS Independent
Classifier: Topic :: Software Development :: Testing
Classifier: Intended Audience :: Developers
Requires-Python: >=3.6
Requires-Dist: pytest (>=5.4)
